nbsqueeze/__init__.py
nbsqueeze/_modidx.py
nbsqueeze/extract.py
nbsqueeze/squeeze.py
nbsqueeze-0.0.2.dist-info/LICENSE
nbsqueeze-0.0.2.dist-info/METADATA
nbsqueeze-0.0.2.dist-info/WHEEL
nbsqueeze-0.0.2.dist-info/entry_points.txt
nbsqueeze-0.0.2.dist-info/top_level.txt
nbsqueeze-0.0.2.dist-info/RECORD
