Metadata-Version: 2.1
Name: nbsqueeze
Version: 0.0.2
Summary: A small Python package to minimize the file size of Jupyter notebooks by extracting figures.
Home-page: https://github.com/fligt/nbsqueeze
Author: Frank Ligterink
Author-email: frank.ligterink@gmail.com
License: MIT License
Keywords: nbdev jupyter notebook python
Platform: UNKNOWN
Classifier: Development Status :: 4 - Beta
Classifier: Intended Audience :: Developers
Classifier: Natural Language :: English
Classifier: Programming Language :: Python :: 3.7
Classifier: Programming Language :: Python :: 3.8
Classifier: Programming Language :: Python :: 3.9
Classifier: Programming Language :: Python :: 3.10
Classifier: License :: OSI Approved :: MIT License
Requires-Python: >=3.7
Requires-Dist: nbformat
Requires-Dist: ipynb-path
Requires-Dist: matplotlib
Requires-Dist: numpy
Provides-Extra: dev
